roadexec/__init__.py
roadexec/exec.py
roadexec/fn.py
roadexec/proc.py
roadexec/run.py
roadexec/shares.py
roadrunner/config.py
roadrunner/fn.py
roadrunner/help.py
roadrunner/log.py
roadrunner/lua.py
roadrunner/rr.py
roadrunner/run.py
roadrunner/tasks.py
roadrunner/version
roadrunner/version.py
roadrunner/assets/__init__.py
roadrunner/assets/__pycache__/__init__.cpython-312.pyc
roadrunner/assets/bender/export.tera
roadrunner/assets/bender/rr.tera
roadrunner/assets/icarus/vpiEntry.c
roadrunner/assets/lua/etlua.lua
roadrunner/assets/rr/__init__.py
roadrunner/assets/rr/logcheck.py
roadrunner/assets/rr/logchecker.py
roadrunner/assets/rr/rrun.py
roadrunner/assets/shell/mainStage.sh
roadrunner/assets/verilator/waiver.vlt
roadrunner/assets/verilog/RREnv.sv
roadrunner/assets/verilog/RRTraceTop.sv
roadrunner/assets/verilog/__init__.py
roadrunner/assets/verilog/rrVpi.cc
roadrunner/assets/vivado/__init__.py
roadrunner/assets/vivado/fn.tcl
roadrunner/assets/vivado/impl.tcl
roadrunner/assets/vivado/ipgen.tcl
roadrunner/assets/vivado/opt.tcl
roadrunner/assets/vivado/physopt.tcl
roadrunner/assets/vivado/place.tcl
roadrunner/assets/vivado/route.tcl
roadrunner/assets/vivado/synth.tcl
roadrunner/assets/vivado/write.tcl
roadrunner/modules/__init__.py
roadrunner/modules/cpp.py
roadrunner/modules/files.py
roadrunner/modules/python.py
roadrunner/modules/stages.py
roadrunner/modules/tcl.py
roadrunner/modules/verilog.py
roadrunner/modules/vhdl.py
roadrunner/runner/__init__.py
roadrunner/runner/local.py
roadrunner/tools/__init__.py
roadrunner/tools/bender.py
roadrunner/tools/builtin.py
roadrunner/tools/fetch.py
roadrunner/tools/flow.py
roadrunner/tools/git.py
roadrunner/tools/icarus.py
roadrunner/tools/icpro.py
roadrunner/tools/python.py
roadrunner/tools/shell.py
roadrunner/tools/slang.py
roadrunner/tools/sv2v.py
roadrunner/tools/verilator.py
roadrunner/tools/vcs/__init__.py
roadrunner/tools/vcs/common.py
roadrunner/tools/vcs/vcsSim.py
roadrunner/tools/vivado/__init__.py
roadrunnereda-4.1.5.dist-info/licenses/LICENSE
roadrunnereda-4.1.5.dist-info/METADATA
roadrunnereda-4.1.5.dist-info/WHEEL
roadrunnereda-4.1.5.dist-info/entry_points.txt
roadrunnereda-4.1.5.dist-info/top_level.txt
roadrunnereda-4.1.5.dist-info/RECORD
