Metadata-Version: 2.4
Name: RoadRunnerEDA
Version: 4.1.5
Summary: EDA project management
Author-email: Mattis Hasler <mattis.hasler@barkhauseninstitut.org>
Maintainer-email: Mattis Hasler <mattis.hasler@barkhauseninstitut.org>
License:                     GNU GENERAL PUBLIC LICENSE
Requires-Python: >=3.9
License-File: LICENSE
Requires-Dist: lupa
Requires-Dist: pyyaml
Requires-Dist: psutil
Dynamic: license-file
